strongtyping_modules/__init__.py
strongtyping_modules/install.py
strongtyping_modules/strongtyping_modules.pyx
strongtyping_modules/sttypingmodule.c
strongtyping_modules-0.1.4.dist-info/LICENSE.md
strongtyping_modules-0.1.4.dist-info/METADATA
strongtyping_modules-0.1.4.dist-info/WHEEL
strongtyping_modules-0.1.4.dist-info/top_level.txt
strongtyping_modules-0.1.4.dist-info/RECORD
