Metadata-Version: 2.1
Name: strongtyping-modules
Version: 0.1.4
Summary: Utils for strongtyping.
Home-page: UNKNOWN
Author: Felix Eisenmenger
Author-email: fberndt87@gmail.com
License: UNKNOWN
Platform: UNKNOWN
Classifier: Programming Language :: Python :: 3
Classifier: License :: OSI Approved :: MIT License
Requires-Dist: Cython (==0.29.21)
